cadvas/__init__.py
cadvas/elements.py
cadvas/widget.py
cadvas-2025.0.1.dist-info/licenses/LICENSE.txt
cadvas-2025.0.1.dist-info/METADATA
cadvas-2025.0.1.dist-info/WHEEL
cadvas-2025.0.1.dist-info/top_level.txt
cadvas-2025.0.1.dist-info/RECORD
